AUTHORS.rst
CHANGES.rst
LICENSE.txt
MANIFEST.in
README.rst
TODO.rst
setup.py
django_secure.egg-info/PKG-INFO
django_secure.egg-info/SOURCES.txt
django_secure.egg-info/dependency_links.txt
django_secure.egg-info/not-zip-safe
django_secure.egg-info/top_level.txt
djangosecure/__init__.py
djangosecure/conf.py
djangosecure/decorators.py
djangosecure/middleware.py
djangosecure/models.py
djangosecure/test_utils.py
djangosecure/tests.py
djangosecure/check/__init__.py
djangosecure/check/csrf.py
djangosecure/check/djangosecure.py
djangosecure/check/run.py
djangosecure/check/sessions.py
djangosecure/check/util.py
djangosecure/management/__init__.py
djangosecure/management/commands/__init__.py
djangosecure/management/commands/checksecure.py
doc/Makefile
doc/changelog.rst
doc/checksecure.rst
doc/conf.py
doc/credits.rst
doc/index.rst
doc/make.bat
doc/middleware.rst
doc/philosophy.rst
doc/settings.rst
doc/todo.rst